dataclass_dateproperty/__init__.py
dataclass_dateproperty/__meta__.py
dataclass_dateproperty/attr_prop.py
dataclass_dateproperty/datetime_utils.py
dataclass_dateproperty/weekdays_list.py
dataclass_dateproperty/__pycache__/__init__.cpython-38.pyc
dataclass_dateproperty/__pycache__/__meta__.cpython-38.pyc
dataclass_dateproperty/__pycache__/attr_prop.cpython-38.pyc
dataclass_dateproperty/__pycache__/datetime_utils.cpython-38.pyc
dataclass_dateproperty/__pycache__/weekdays_list.cpython-38.pyc
dataclass_dateproperty-1.0.0.dist-info/LICENSE
dataclass_dateproperty-1.0.0.dist-info/METADATA
dataclass_dateproperty-1.0.0.dist-info/WHEEL
dataclass_dateproperty-1.0.0.dist-info/top_level.txt
dataclass_dateproperty-1.0.0.dist-info/RECORD
