Metadata-Version: 2.1
Name: dataclass-dateproperty
Version: 1.0.0
Summary: Weekdays and datetime properties for the dataclass_property library.
Home-page: https://github.com/justengel/dataclass_dateproperty
Author: Justin Engel
Author-email: jtengel08@gmail.com
License: MIT
Download-URL: https://github.com/justengel/dataclass_dateproperty/archive/v1.0.0.tar.gz
Keywords: dataclasses dataclass property field_property weekdays datetime
Platform: any
Classifier: Programming Language :: Python
Classifier: Programming Language :: Python :: 3
Classifier: Operating System :: OS Independent
Requires-Dist: dataclass-property (>=1.2.0)
